COPYING
COPYING.lesser
MANIFEST.in
NOTICE
README.md
requirements.txt
setup.py
compiler/__init__.py
compiler/api/__init__.py
compiler/api/compiler.py
compiler/api/source/auth_key.tl
compiler/api/source/main_api.tl
compiler/api/source/sys_msgs.tl
compiler/api/template/combinator.txt
compiler/api/template/type.txt
compiler/docs/__init__.py
compiler/docs/compiler.py
compiler/docs/template/page.txt
compiler/docs/template/toctree.txt
compiler/errors/__init__.py
compiler/errors/compiler.py
compiler/errors/sort.py
compiler/errors/source/303_SEE_OTHER.tsv
compiler/errors/source/400_BAD_REQUEST.tsv
compiler/errors/source/401_UNAUTHORIZED.tsv
compiler/errors/source/403_FORBIDDEN.tsv
compiler/errors/source/406_NOT_ACCEPTABLE.tsv
compiler/errors/source/420_FLOOD.tsv
compiler/errors/source/500_INTERNAL_SERVER_ERROR.tsv
compiler/errors/source/503_SERVICE_UNAVAILABLE.tsv
compiler/errors/template/class.txt
compiler/errors/template/sub_class.txt
ingram/__init__.py
ingram/client.py
ingram/dispatcher.py
ingram/emoji.py
ingram/file_id.py
ingram/filters.py
ingram/mime_types.py
ingram/py.typed
ingram/sync.py
ingram/utils.py
ingram.egg-info/PKG-INFO
ingram.egg-info/SOURCES.txt
ingram.egg-info/dependency_links.txt
ingram.egg-info/not-zip-safe
ingram.egg-info/requires.txt
ingram.egg-info/top_level.txt
ingram/connection/__init__.py
ingram/connection/connection.py
ingram/connection/transport/__init__.py
ingram/connection/transport/tcp/__init__.py
ingram/connection/transport/tcp/tcp.py
ingram/connection/transport/tcp/tcp_abridged.py
ingram/connection/transport/tcp/tcp_abridged_o.py
ingram/connection/transport/tcp/tcp_full.py
ingram/connection/transport/tcp/tcp_intermediate.py
ingram/connection/transport/tcp/tcp_intermediate_o.py
ingram/crypto/__init__.py
ingram/crypto/aes.py
ingram/crypto/mtproto.py
ingram/crypto/prime.py
ingram/crypto/rsa.py
ingram/enums/__init__.py
ingram/enums/auto_name.py
ingram/enums/chat_action.py
ingram/enums/chat_event_action.py
ingram/enums/chat_member_status.py
ingram/enums/chat_members_filter.py
ingram/enums/chat_type.py
ingram/enums/message_entity_type.py
ingram/enums/message_media_type.py
ingram/enums/message_service_type.py
